lookout_config/__init__.py
lookout_config/config_io.py
lookout_config/generate_schemas.py
lookout_config/helpers.py
lookout_config/launch_parameters.py
lookout_config/types.py
lookout_config/schemas/lookout.schema.json
lookout_config/test/test_config_io.py
lookout_config-3.0.1.dist-info/METADATA
lookout_config-3.0.1.dist-info/WHEEL
lookout_config-3.0.1.dist-info/top_level.txt
lookout_config-3.0.1.dist-info/zip-safe
lookout_config-3.0.1.dist-info/RECORD
