Metadata-Version: 2.4
Name: lookout_config
Version: 3.0.1
Summary: A library for reading / writing Lookout config files
Author-email: Greenroom Robotics <team@greenroomrobotics.com>
Maintainer-email: David Revay <david.revay@greenroomrobotics.com>
License: Copyright (C) 2025, Greenroom Robotics
Project-URL: homepage, https://github.com/Greenroom-Robotics/lookout
Keywords: colcon
Classifier: Development Status :: 3 - Alpha
Classifier: Environment :: Plugins
Classifier: Intended Audience :: Developers
Classifier: Programming Language :: Python
Classifier: Topic :: Software Development :: Build Tools
Requires-Dist: setuptools
Requires-Dist: PyYAML
Requires-Dist: greenstream-config>=4.0.0
Requires-Dist: pydantic
